vmtui/__init__.py
vmtui/gen_libvirt_polkit_acl.py
vmtui/vmtui.py
vmtui/static/__init__.py
vmtui/static/vmtui.css
vmtui-0.9.5.dist-info/AUTHORS
vmtui-0.9.5.dist-info/METADATA
vmtui-0.9.5.dist-info/WHEEL
vmtui-0.9.5.dist-info/entry_points.txt
vmtui-0.9.5.dist-info/pbr.json
vmtui-0.9.5.dist-info/top_level.txt
vmtui-0.9.5.dist-info/RECORD
