Metadata-Version: 2.1
Name: vmtui
Version: 0.9.5
Summary: A text user interface (TUI) to control virtual machines on a per user basis
Home-page: https://github.com/cgruhl/vmtui
Author: Christian Gruhl
Author-email: cgruhl@uni-kassel.de
Keywords: libvirt,KVM,VM
Classifier: Development Status :: 4 - Beta
Classifier: Intended Audience :: Developers
Classifier: Programming Language :: Python
License-File: AUTHORS
Requires-Dist: libvirt-python >=10.0.0
Requires-Dist: textual >=0.73.0
Requires-Dist: pyyaml >=6.0.0
